pybgh/__init__.py
pybgh-0.1.4.dist-info/LICENSE
pybgh-0.1.4.dist-info/METADATA
pybgh-0.1.4.dist-info/WHEEL
pybgh-0.1.4.dist-info/top_level.txt
pybgh-0.1.4.dist-info/RECORD
